gemini_tl/__init__.py
gemini_tl/config.py
gemini_tl/gemini.py
gemini_tl/main.py
gemini_tl/models.py
gemini_tl/video.py
gemini_tl-0.0.5.dist-info/licenses/LICENSE
gemini_tl-0.0.5.dist-info/METADATA
gemini_tl-0.0.5.dist-info/WHEEL
gemini_tl-0.0.5.dist-info/entry_points.txt
gemini_tl-0.0.5.dist-info/top_level.txt
gemini_tl-0.0.5.dist-info/RECORD
