Metadata-Version: 2.4
Name: gemini-tl
Version: 0.0.5
Summary: Generate and translate English and Japanese subtitles using Google Gemini AI.
Author: FlippFuzz
Project-URL: Homepage, https://github.com/FlippFuzz/gemini-tl
Project-URL: Bug Tracker, https://github.com/FlippFuzz/gemini-tl/issues
Requires-Python: >=3.10
License-File: LICENSE
Requires-Dist: pysubs2
Requires-Dist: google-genai
Requires-Dist: static-ffmpeg
Requires-Dist: pymediainfo
Requires-Dist: json-repair
Requires-Dist: pathvalidate
Requires-Dist: pydantic
Requires-Dist: retrying
Dynamic: license-file
